{"name":"Should be able to clear completed items","id":"completing-todos;should-be-able-to-clear-completed-items","scenarioId":"classpath:features/cucumber/maintain_my_todo_list/completing_todos:Should be able to clear completed items","methodName":"Should be able to clear completed items","testSteps":[{"number":1,"description":"Given that Jane has a todo list containing Buy some milk, Walk the dog","duration":13567,"startTime":"2023-12-03T18:46:28.909857410Z[Etc/UTC]","screenshots":[{"screenshot":"1755ce4c1c7e16b9e1045b8d5154f56560bfda7cbd70d1522c69ff90eaa38da2.png","timeStamp":1701629202478,"screenshotName":"1755ce4c1c7e16b9e1045b8d5154f56560bfda7cbd70d1522c69ff90eaa38da2.png"}],"result":"SUCCESS","precondition":false,"level":0,"children":[{"number":2,"description":"Jane starts with a todo list containing Buy some milk, Walk the dog","duration":13333,"startTime":"2023-12-03T18:46:29.143535805Z[Etc/UTC]","screenshots":[{"screenshot":"1755ce4c1c7e16b9e1045b8d5154f56560bfda7cbd70d1522c69ff90eaa38da2.png","timeStamp":1701629202476,"screenshotName":"1755ce4c1c7e16b9e1045b8d5154f56560bfda7cbd70d1522c69ff90eaa38da2.png"}],"result":"SUCCESS","precondition":false,"level":1,"children":[{"number":3,"description":"Jane opens the home.page page","duration":11824,"startTime":"2023-12-03T18:46:29.158776841Z[Etc/UTC]","screenshots":[{"screenshot":"78c96d8ffa1411bf136fbeab1103990b21beb89ffaf7f7ef5f284a69d4e7d0ca.png","timeStamp":1701629200982,"screenshotName":"78c96d8ffa1411bf136fbeab1103990b21beb89ffaf7f7ef5f284a69d4e7d0ca.png"}],"result":"SUCCESS","precondition":false,"level":2},{"number":4,"description":"Jane adds the todo items called: [Buy some milk, Walk the dog]","duration":1479,"startTime":"2023-12-03T18:46:40.994648216Z[Etc/UTC]","screenshots":[{"screenshot":"1755ce4c1c7e16b9e1045b8d5154f56560bfda7cbd70d1522c69ff90eaa38da2.png","timeStamp":1701629202473,"screenshotName":"1755ce4c1c7e16b9e1045b8d5154f56560bfda7cbd70d1522c69ff90eaa38da2.png"}],"result":"SUCCESS","precondition":false,"level":2,"children":[{"number":5,"description":"Jane adds a todo item called: Buy some milk","duration":797,"startTime":"2023-12-03T18:46:41.014898496Z[Etc/UTC]","screenshots":[{"screenshot":"ff7f15e6c018db1a43688f692a1da47d746697f35b8ef9d8af58cf1c902881bd.png","timeStamp":1701629201812,"screenshotName":"ff7f15e6c018db1a43688f692a1da47d746697f35b8ef9d8af58cf1c902881bd.png"}],"result":"SUCCESS","precondition":false,"level":3,"children":[{"number":6,"description":"Jane enters \u0027Buy some milk\u0027 then hits [RETURN] into \u0027What needs to be done?\u0027 field","duration":788,"startTime":"2023-12-03T18:46:41.016486948Z[Etc/UTC]","screenshots":[{"screenshot":"ff7f15e6c018db1a43688f692a1da47d746697f35b8ef9d8af58cf1c902881bd.png","timeStamp":1701629201804,"screenshotName":"ff7f15e6c018db1a43688f692a1da47d746697f35b8ef9d8af58cf1c902881bd.png"}],"result":"SUCCESS","precondition":false,"level":4}]},{"number":7,"description":"Jane adds a todo item called: Walk the dog","duration":653,"startTime":"2023-12-03T18:46:41.816251086Z[Etc/UTC]","screenshots":[{"screenshot":"1755ce4c1c7e16b9e1045b8d5154f56560bfda7cbd70d1522c69ff90eaa38da2.png","timeStamp":1701629202469,"screenshotName":"1755ce4c1c7e16b9e1045b8d5154f56560bfda7cbd70d1522c69ff90eaa38da2.png"}],"result":"SUCCESS","precondition":false,"level":3,"children":[{"number":8,"description":"Jane enters \u0027Walk the dog\u0027 then hits [RETURN] into \u0027What needs to be done?\u0027 field","duration":646,"startTime":"2023-12-03T18:46:41.817963940Z[Etc/UTC]","screenshots":[{"screenshot":"1755ce4c1c7e16b9e1045b8d5154f56560bfda7cbd70d1522c69ff90eaa38da2.png","timeStamp":1701629202464,"screenshotName":"1755ce4c1c7e16b9e1045b8d5154f56560bfda7cbd70d1522c69ff90eaa38da2.png"}],"result":"SUCCESS","precondition":false,"level":4}]}]}]}]},{"number":9,"description":"When she completes the task called \"Walk the dog\"","duration":562,"startTime":"2023-12-03T18:46:42.479215090Z[Etc/UTC]","screenshots":[{"screenshot":"83a5745de4b74b09a88360684117f727daed15a74ac2e814299a233c6e89dafa.png","timeStamp":1701629203043,"screenshotName":"83a5745de4b74b09a88360684117f727daed15a74ac2e814299a233c6e89dafa.png"}],"result":"SUCCESS","precondition":false,"level":0,"children":[{"number":10,"description":"she completes the item calledWalk the dog","duration":558,"startTime":"2023-12-03T18:46:42.482995850Z[Etc/UTC]","screenshots":[{"screenshot":"83a5745de4b74b09a88360684117f727daed15a74ac2e814299a233c6e89dafa.png","timeStamp":1701629203041,"screenshotName":"83a5745de4b74b09a88360684117f727daed15a74ac2e814299a233c6e89dafa.png"}],"result":"SUCCESS","precondition":false,"level":1,"children":[{"number":11,"description":"she clicks on the complete item tick box","duration":554,"startTime":"2023-12-03T18:46:42.484124916Z[Etc/UTC]","screenshots":[{"screenshot":"83a5745de4b74b09a88360684117f727daed15a74ac2e814299a233c6e89dafa.png","timeStamp":1701629203038,"screenshotName":"83a5745de4b74b09a88360684117f727daed15a74ac2e814299a233c6e89dafa.png"}],"result":"SUCCESS","precondition":false,"level":2}]}]},{"number":12,"description":"And she clears the completed items","duration":4462,"startTime":"2023-12-03T18:46:43.043867973Z[Etc/UTC]","screenshots":[{"screenshot":"272518e5abc4541b43057c695c79488ba5cab94e2cc062c4a2c72e9db78b1b09.png","timeStamp":1701629207943,"screenshotName":"272518e5abc4541b43057c695c79488ba5cab94e2cc062c4a2c72e9db78b1b09.png"}],"result":"SUCCESS","precondition":false,"level":0,"children":[{"number":13,"description":"she clears all the completed items","duration":839,"startTime":"2023-12-03T18:46:43.049754573Z[Etc/UTC]","screenshots":[{"screenshot":"272518e5abc4541b43057c695c79488ba5cab94e2cc062c4a2c72e9db78b1b09.png","timeStamp":1701629203889,"screenshotName":"272518e5abc4541b43057c695c79488ba5cab94e2cc062c4a2c72e9db78b1b09.png"}],"result":"SUCCESS","precondition":false,"level":1,"children":[{"number":14,"description":"she clicks on Clear completed link","duration":834,"startTime":"2023-12-03T18:46:43.052477627Z[Etc/UTC]","screenshots":[{"screenshot":"272518e5abc4541b43057c695c79488ba5cab94e2cc062c4a2c72e9db78b1b09.png","timeStamp":1701629203886,"screenshotName":"272518e5abc4541b43057c695c79488ba5cab94e2cc062c4a2c72e9db78b1b09.png"}],"result":"SUCCESS","precondition":false,"level":2}]}]},{"number":15,"description":"Then her todo list should contain Buy some milk","duration":2442,"startTime":"2023-12-03T18:46:47.943660775Z[Etc/UTC]","screenshots":[{"screenshot":"272518e5abc4541b43057c695c79488ba5cab94e2cc062c4a2c72e9db78b1b09.png","timeStamp":1701629210721,"screenshotName":"272518e5abc4541b43057c695c79488ba5cab94e2cc062c4a2c72e9db78b1b09.png"}],"result":"SUCCESS","precondition":false,"level":0,"children":[{"number":16,"description":"Then the items displayed should be ([Buy some milk])","duration":163,"startTime":"2023-12-03T18:46:47.944765245Z[Etc/UTC]","result":"SUCCESS","precondition":false,"level":1}]}],"userStory":{"id":"classpath:features/cucumber/maintain_my_todo_list/completing_todos","storyName":"Completing todos","displayName":"Completing todos","path":"cucumber/maintain_my_todo_list/completing_todos","pathElements":[{"name":"cucumber","description":""},{"name":"maintain_my_todo_list","description":""},{"name":"completing_todos","description":""}],"narrative":"  In order to make me feel **a sense of accomplishment**\n  As a forgetful person\n  I want to be to _view all of things I have completed_","type":"feature"},"title":"Should be able to clear completed items","description":"","tags":[{"name":"cucumber","type":"tag","displayName":"cucumber"},{"name":"completing","type":"tag","displayName":"completing"},{"name":"Edge","type":"context","displayName":"Edge"}],"startTime":"2023-12-03T18:46:28.849063319Z[Etc/UTC]","duration":21872,"projectKey":"","sessionId":"135c243d14d902224738e3808962fa8ad5c003fa","driver":"remote:jane","isManualTestingUpToDate":false,"context":"edge","manual":false,"testSource":"Cucumber","actors":[{"name":"Jane"}],"externalLink":{"type":"BrowserStack"},"result":"SUCCESS"}